FPV/__init__.py
FPV/API/__init__.py
FPV/API/api.py
FPV/API/routes/__init__.py
FPV/API/routes/path/__init__.py
FPV/API/routes/path/clean.py
FPV/API/routes/path/dynamic.py
FPV/API/routes/path/isValid.py
FPV/Helpers/__init__.py
FPV/Helpers/_base.py
FPV/Helpers/_path.py
FPV/Helpers/box.py
FPV/Helpers/dropbox.py
FPV/Helpers/egnyte.py
FPV/Helpers/onedrive.py
FPV/Helpers/os_classes.py
FPV/Helpers/sharefile.py
FPV/Helpers/sharepoint.py
FPV/Tests/__init__.py
FPV/Tests/test_base_service.py
FPV/Tests/test_egnyte.py
FPV/Tests/test_onedrive.py
FPV/Tests/test_os_classes.py
FPV/Tests/test_path.py
file_path_validator-3.1.2.dist-info/licenses/LICENSE
file_path_validator-3.1.2.dist-info/METADATA
file_path_validator-3.1.2.dist-info/WHEEL
file_path_validator-3.1.2.dist-info/top_level.txt
file_path_validator-3.1.2.dist-info/RECORD
