Metadata-Version: 2.4
Name: file-path-validator
Version: 3.1.2
Summary: A package for validating file paths across different operating systems and storage services.
Home-page: https://github.com/Voltaic314/File_Path_Validator
Author: Logan
Author-email: lmaupin754@gmail.com
License: MIT
Classifier: Programming Language :: Python :: 3
Classifier: License :: OSI Approved :: MIT License
Classifier: Operating System :: OS Independent
Requires-Python: >=3.6
License-File: LICENSE
Requires-Dist: colorama==0.4.6
Requires-Dist: exceptiongroup==1.2.2
Requires-Dist: iniconfig==2.0.0
Requires-Dist: packaging==24.1
Requires-Dist: pluggy==1.5.0
Requires-Dist: pytest==8.3.3
Requires-Dist: tomli==2.0.2
Requires-Dist: Quart==0.20.0
Requires-Dist: typing_extensions==4.14.0
Dynamic: author
Dynamic: author-email
Dynamic: classifier
Dynamic: description
Dynamic: description-content-type
Dynamic: home-page
Dynamic: license
Dynamic: license-file
Dynamic: requires-dist
Dynamic: requires-python
Dynamic: summary
